emmpy/__init__.py
emmpy/emmpy.py
emmpy-0.0.1.dist-info/LICENSE
emmpy-0.0.1.dist-info/METADATA
emmpy-0.0.1.dist-info/WHEEL
emmpy-0.0.1.dist-info/top_level.txt
emmpy-0.0.1.dist-info/RECORD
