Metadata-Version: 2.1
Name: emmpy
Version: 0.0.1
Summary: Empirical Magnetic Modeling for Python
Home-page: https://github.com/ewinterapl/emmpy
Author: Eric Winter
Author-email: eric.winter@jhuapl.edu
License: UNKNOWN
Platform: UNKNOWN
Classifier: Programming Language :: Python :: 3
Classifier: License :: OSI Approved :: MIT License
Classifier: Operating System :: OS Independent
Requires-Python: >=3.6
